audit_log/__init__.py
audit_log/decorators.py
audit_log/middleware.py
audit_log/registration.py
audit_log/settings.py
audit_log/models/__init__.py
audit_log/models/fields.py
audit_log/models/managers.py
audit_log/tests/__init__.py
audit_log/tests/runtests.py
audit_log/tests/runtests_custom_auth.py
audit_log/tests/urls.py
audit_log/tests/audit_log_tests/__init__.py
audit_log/tests/audit_log_tests/models.py
audit_log/tests/audit_log_tests/test_logging.py
audit_log/tests/audit_log_tests/test_manager.py
audit_log/tests/audit_log_tests/views.py
django_audit_log2-0.8.0.dist-info/AUTHORS.txt
django_audit_log2-0.8.0.dist-info/LICENSE.txt
django_audit_log2-0.8.0.dist-info/METADATA
django_audit_log2-0.8.0.dist-info/WHEEL
django_audit_log2-0.8.0.dist-info/top_level.txt
django_audit_log2-0.8.0.dist-info/RECORD
