Metadata-Version: 2.1
Name: django-audit-log2
Version: 0.8.0
Summary: Audit trail for django models
Home-page: https://github.com/Atomidata/django-audit-log
Download-URL: https://github.com/Atomidata/django-audit-log/downloads
Author: Vasil Vangelovski
Author-email: vvangelovski@gmail.com
License: New BSD License (http://www.opensource.org/licenses/bsd-license.php)
Classifier: Development Status :: 5 - Production/Stable
Classifier: Environment :: Plugins
Classifier: Framework :: Django
Classifier: Intended Audience :: Developers
Classifier: License :: OSI Approved :: BSD License
Classifier: Topic :: Software Development :: Libraries :: Python Modules
Classifier: Programming Language :: Python
Classifier: Programming Language :: Python :: 2.6
Classifier: Programming Language :: Python :: 2.7
Classifier: Programming Language :: Python :: 3
Classifier: Programming Language :: Python :: 3.2
Classifier: Programming Language :: Python :: 3.3
Classifier: Programming Language :: Python :: 3.4
License-File: LICENSE.txt
License-File: AUTHORS.txt
